tests/test_toolset.py
toolsed/__init__.py
toolsed/dicttools.py
toolsed/functions.py
toolsed/listtools.py
toolsed/stringtools.py
toolsed-0.3.0.dist-info/licenses/LICENSE
toolsed-0.3.0.dist-info/METADATA
toolsed-0.3.0.dist-info/WHEEL
toolsed-0.3.0.dist-info/top_level.txt
toolsed-0.3.0.dist-info/RECORD
