Metadata-Version: 2.4
Name: toolsed
Version: 0.3.0
Summary: A collection of tools for developers
Author-email: Froki <iroorp32@gmail.com>
License: MIT
Project-URL: Homepage, https://github.com/Frokich/Toolsed
Project-URL: Repository, https://github.com/Frokich/Toolsed
Classifier: Development Status :: 3 - Alpha
Classifier: Intended Audience :: Developers
Classifier: License :: OSI Approved :: MIT License
Classifier: Programming Language :: Python
Requires-Python: >=3.7
License-File: LICENSE
Dynamic: license-file
